onegadget_selector/__init__.py
onegadget_selector/formatter.py
onegadget_selector/selector.py
onegadget_selector-0.1.2.dist-info/licenses/LICENSE
onegadget_selector-0.1.2.dist-info/METADATA
onegadget_selector-0.1.2.dist-info/WHEEL
onegadget_selector-0.1.2.dist-info/top_level.txt
onegadget_selector-0.1.2.dist-info/RECORD
