Metadata-Version: 2.4
Name: onegadget-selector
Version: 0.1.2
Summary: A terminal UI tool for selecting OneGadgets with syntax highlighting.
Author-email: RatherHard <usury43@qq.com>
License: MIT
Project-URL: Homepage, https://github.com/RatherHard/onegadget-selector
Project-URL: Bug Tracker, https://github.com/RatherHard/onegadget-selector/issues
Keywords: pwn,onegadget,ctf,tui,questionary
Classifier: Programming Language :: Python :: 3
Classifier: License :: OSI Approved :: MIT License
Classifier: Operating System :: OS Independent
Classifier: Topic :: Security
Requires-Python: >=3.7
License-File: LICENSE
Requires-Dist: questionary>=2.0.0
Requires-Dist: prompt-toolkit>=3.0.0
Requires-Dist: pwntools>=3.0.0
Dynamic: license-file
